playgodot/__init__.py
playgodot/exceptions.py
playgodot/godot.py
playgodot/native_client.py
playgodot/native_input.py
playgodot/node.py
playgodot/py.typed
playgodot/variant.py
playgodot-0.5.1.dist-info/METADATA
playgodot-0.5.1.dist-info/WHEEL
playgodot-0.5.1.dist-info/RECORD
